pretix_pix_openpix/__init__.py
pretix_pix_openpix/apps.py
pretix_pix_openpix/payment.py
pretix_pix_openpix/pix.py
pretix_pix_openpix/signals.py
pretix_pix_openpix/urls.py
pretix_pix_openpix/views.py
pretix_pix_openpix/locale/pt_BR/LC_MESSAGES/django.mo
pretix_pix_openpix/locale/pt_BR/LC_MESSAGES/django.po
pretix_pix_openpix/static/pretix_pix_manual/.gitkeep
pretix_pix_openpix/templates/pretix_pix_openpix/checkout_confirm.html
pretix_pix_openpix/templates/pretix_pix_openpix/payment_pending.html
pretix_pix_openpix-0.2.0.dist-info/licenses/LICENSE
pretix_pix_openpix-0.2.0.dist-info/METADATA
pretix_pix_openpix-0.2.0.dist-info/WHEEL
pretix_pix_openpix-0.2.0.dist-info/entry_points.txt
pretix_pix_openpix-0.2.0.dist-info/top_level.txt
pretix_pix_openpix-0.2.0.dist-info/RECORD
